openfund_plugin_up/__init__.py
openfund_plugin_up/command.py
openfund_plugin_up/plugin.py
openfund_plugin_up-0.0.2.dist-info/LICENSE
openfund_plugin_up-0.0.2.dist-info/METADATA
openfund_plugin_up-0.0.2.dist-info/WHEEL
openfund_plugin_up-0.0.2.dist-info/entry_points.txt
openfund_plugin_up-0.0.2.dist-info/RECORD
