Metadata-Version: 2.1
Name: openfund-plugin-up
Version: 0.0.2
Summary: Openfund plugin that updates dependencies and bumps their versions in pyproject.toml file
License: MIT
Keywords: packaging,dependency,openfund,update,upgrade
Author: yang99love
Requires-Python: >=3.8,<4.0
Classifier: Development Status :: 5 - Production/Stable
Classifier: License :: OSI Approved :: MIT License
Classifier: Operating System :: OS Independent
Classifier: Programming Language :: Python :: 3
Classifier: Programming Language :: Python :: 3.8
Classifier: Programming Language :: Python :: 3.9
Classifier: Programming Language :: Python :: 3.10
Classifier: Programming Language :: Python :: 3.11
Classifier: Programming Language :: Python :: 3.12
Classifier: Programming Language :: Python :: 3.13
Requires-Dist: openfund (>=0.1.6,<0.2.0)
